transpilex/__init__.py
transpilex/main.py
transpilex/cli/__init__.py
transpilex/cli/prompts.py
transpilex/config/__init__.py
transpilex/config/base.py
transpilex/config/package.py
transpilex/config/project.py
transpilex/frameworks/__init__.py
transpilex/frameworks/blazor.py
transpilex/frameworks/cakephp.py
transpilex/frameworks/codeigniter.py
transpilex/frameworks/core.py
transpilex/frameworks/django.py
transpilex/frameworks/flask.py
transpilex/frameworks/laravel.py
transpilex/frameworks/mvc.py
transpilex/frameworks/node.py
transpilex/frameworks/php.py
transpilex/frameworks/ror.py
transpilex/frameworks/spring.py
transpilex/frameworks/symfony.py
transpilex/patterns/import_patterns.json
transpilex/patterns/variable_patterns.json
transpilex/templates/node-app.js
transpilex/templates/php-tw-vite.config.js
transpilex/utils/__init__.py
transpilex/utils/assets.py
transpilex/utils/casing.py
transpilex/utils/extract_fragments.py
transpilex/utils/file.py
transpilex/utils/git.py
transpilex/utils/gulpfile.py
transpilex/utils/logs.py
transpilex/utils/package_json.py
transpilex/utils/pattern.py
transpilex/utils/replace_html_links.py
transpilex/utils/replace_variables.py
transpilex/utils/restructure.py
transpilex/utils/template.py
transpilex-1.2.0.dist-info/METADATA
transpilex-1.2.0.dist-info/WHEEL
transpilex-1.2.0.dist-info/entry_points.txt
transpilex-1.2.0.dist-info/top_level.txt
transpilex-1.2.0.dist-info/RECORD
