Metadata-Version: 2.4
Name: transpilex
Version: 1.2.0
Summary: Transpile HTML into given frameworks
Author: Anant Navadiya
Author-email: contact@anantnavadiya.com
License: MIT
Requires-Dist: arrow==1.4.0
Requires-Dist: beautifulsoup4==4.14.2
Requires-Dist: binaryornot==0.4.4
Requires-Dist: bs4==0.0.2
Requires-Dist: certifi==2025.10.5
Requires-Dist: chardet==5.2.0
Requires-Dist: charset-normalizer==3.4.4
Requires-Dist: click==8.3.0
Requires-Dist: colorama==0.4.6
Requires-Dist: cookiecutter==2.6.0
Requires-Dist: docutils==0.22.3
Requires-Dist: id==1.5.0
Requires-Dist: idna==3.11
Requires-Dist: jaraco.classes==3.4.0
Requires-Dist: jaraco.context==6.0.1
Requires-Dist: jaraco.functools==4.3.0
Requires-Dist: Jinja2==3.1.6
Requires-Dist: keyring==25.7.0
Requires-Dist: markdown-it-py==4.0.0
Requires-Dist: MarkupSafe==3.0.3
Requires-Dist: mdurl==0.1.2
Requires-Dist: more-itertools==10.8.0
Requires-Dist: nh3==0.3.2
Requires-Dist: packaging==25.0
Requires-Dist: prompt_toolkit==3.0.52
Requires-Dist: Pygments==2.19.2
Requires-Dist: python-dateutil==2.9.0.post0
Requires-Dist: python-slugify==8.0.4
Requires-Dist: pywin32-ctypes==0.2.3
Requires-Dist: PyYAML==6.0.3
Requires-Dist: questionary==2.1.1
Requires-Dist: readme_renderer==44.0
Requires-Dist: requests==2.32.5
Requires-Dist: requests-toolbelt==1.0.0
Requires-Dist: rfc3986==2.0.0
Requires-Dist: rich==14.2.0
Requires-Dist: setuptools==80.9.0
Requires-Dist: six==1.17.0
Requires-Dist: soupsieve==2.8
Requires-Dist: text-unidecode==1.3
Requires-Dist: twine==6.2.0
Requires-Dist: typing_extensions==4.15.0
Requires-Dist: tzdata==2025.2
Requires-Dist: urllib3==2.5.0
Requires-Dist: wcwidth==0.2.14
Requires-Dist: wheel==0.45.1
Dynamic: author
Dynamic: author-email
Dynamic: license
Dynamic: requires-dist
Dynamic: summary
